MANIFEST.in
README.rst
requirements.txt
setup.py
pyux/__init__.py
pyux/__main__.py
pyux/__utils__.py
pyux/console.py
pyux/errors.py
pyux/logging.conf
pyux/logging.py
pyux/time.py
pyux/demo/__init__.py
pyux/demo/interact.py
pyux/demo/messages.py
pyux/demo/write.py
pyux/demo/modules/__init__.py
pyux/demo/modules/console.py
pyux/demo/modules/logging.py
pyux/demo/modules/time.py
pyux_track.egg-info/PKG-INFO
pyux_track.egg-info/SOURCES.txt
pyux_track.egg-info/dependency_links.txt
pyux_track.egg-info/requires.txt
pyux_track.egg-info/top_level.txt