Metadata-Version: 2.1
Name: pyux-track
Version: 0.1.4
Summary: Python ux tools to ease tracking scripts
Home-page: https://pyux.readthedocs.io/en/stable/
Author: Romain Damian
Author-email: damian.romain@gmail.com
License: UNKNOWN
Platform: UNKNOWN
